ioamdoit/__init__.py
ioamdoit/_version.py
ioamdoit-0.0.8.dist-info/DESCRIPTION.rst
ioamdoit-0.0.8.dist-info/METADATA
ioamdoit-0.0.8.dist-info/RECORD
ioamdoit-0.0.8.dist-info/WHEEL
ioamdoit-0.0.8.dist-info/metadata.json
ioamdoit-0.0.8.dist-info/top_level.txt
