Metadata-Version: 2.0
Name: ioamdoit
Version: 0.0.8
Summary: common ioam doit tasks
Home-page: http://github.com/ioam/ioamdoit
Author: UNKNOWN
Author-email: UNKNOWN
License: MIT
Platform: UNKNOWN
Requires-Dist: doit
